mindustry_campaign_stats/__init__.py
mindustry_campaign_stats/__version__.py
mindustry_campaign_stats/cli.py
mindustry_campaign_stats/constants.py
mindustry_campaign_stats/presenters.py
mindustry_campaign_stats/settings.py
mindustry_campaign_stats/stats.py
mindustry_campaign_stats-2.1.1.dist-info/licenses/LICENSE.md
mindustry_campaign_stats-2.1.1.dist-info/METADATA
mindustry_campaign_stats-2.1.1.dist-info/WHEEL
mindustry_campaign_stats-2.1.1.dist-info/entry_points.txt
mindustry_campaign_stats-2.1.1.dist-info/top_level.txt
mindustry_campaign_stats-2.1.1.dist-info/RECORD
