Metadata-Version: 2.4
Name: mindustry-campaign-stats
Version: 2.1.1
Summary: Python API and CLI tool to read Mindustry's campaign global stats.
Home-page: https://github.com/EpocDotFr/mindustry-campaign-stats
Author: Maxime "Epoc" Gross
Author-email: contact.nospam@epoc.nospam.fr
License: DBAD
Project-URL: Documentation, https://github.com/EpocDotFr/mindustry-campaign-stats?tab=readme-ov-file#usage
Project-URL: Source code, https://github.com/EpocDotFr/mindustry-campaign-stats
Project-URL: Issue tracker, https://github.com/EpocDotFr/mindustry-campaign-stats/issues
Project-URL: Changelog, https://github.com/EpocDotFr/mindustry-campaign-stats/releases
Keywords: mindustry,settings,reader,stats
Classifier: Development Status :: 5 - Production/Stable
Classifier: Operating System :: OS Independent
Classifier: Environment :: Console
Classifier: Topic :: Games/Entertainment
Classifier: Topic :: File Formats
Classifier: Programming Language :: Python :: 3.10
Classifier: Programming Language :: Python :: 3.11
Classifier: Programming Language :: Python :: 3.12
Classifier: Intended Audience :: Developers
Requires-Python: >=3.10
License-File: LICENSE.md
Requires-Dist: rich~=14.0
Requires-Dist: mutf8~=1.0
Requires-Dist: py-ubjson~=0.16
Requires-Dist: watchdog~=6.0
Provides-Extra: dev
Requires-Dist: twine~=6.0; extra == "dev"
Requires-Dist: build~=1.2; extra == "dev"
Requires-Dist: setuptools>=69; extra == "dev"
Dynamic: author
Dynamic: author-email
Dynamic: classifier
Dynamic: description
Dynamic: description-content-type
Dynamic: home-page
Dynamic: keywords
Dynamic: license
Dynamic: license-file
Dynamic: project-url
Dynamic: provides-extra
Dynamic: requires-dist
Dynamic: requires-python
Dynamic: summary
